blitzrank/__init__.py
blitzrank-0.0.2.dist-info/METADATA
blitzrank-0.0.2.dist-info/WHEEL
blitzrank-0.0.2.dist-info/licenses/LICENSE
blitzrank-0.0.2.dist-info/RECORD
