Metadata-Version: 2.4
Name: blitzrank
Version: 0.0.2
Summary: A fast and efficient reranking library for ML applications
Project-URL: Homepage, https://github.com/sheshansh/blitzrank
Project-URL: Issues, https://github.com/sheshansh/blitzrank/issues
Author: Sheshansh Agrawal
License: MIT
License-File: LICENSE
Keywords: machine-learning,ml,ranking,reranking,search
Classifier: Development Status :: 1 - Planning
Classifier: Intended Audience :: Developers
Classifier: Intended Audience :: Science/Research
Classifier: License :: OSI Approved :: MIT License
Classifier: Operating System :: OS Independent
Classifier: Programming Language :: Python :: 3
Classifier: Programming Language :: Python :: 3.8
Classifier: Programming Language :: Python :: 3.9
Classifier: Programming Language :: Python :: 3.10
Classifier: Programming Language :: Python :: 3.11
Classifier: Programming Language :: Python :: 3.12
Classifier: Topic :: Scientific/Engineering :: Artificial Intelligence
Requires-Python: >=3.8
